[
  {
    "querie": "faculte des science ben m'sik",
    "urls": [
      "http://www.fsb.univh2c.ma/"
    ],
    "metas": [
      {
        "url": "http://www.fsb.univh2c.ma/",
        "keywords": "",
        "description": "",
        "emails": []
      },
      {
        "url": "http://www.fsb.univh2c.ma/?page_id=1138",
        "keywords": "",
        "description": "",
        "emails": []
      },
      {
        "url": "http://www.fsb.univh2c.ma/?page_id=2",
        "keywords": "",
        "description": "",
        "emails": []
      },
      {
        "url": "http://www.fsb.univh2c.ma/?page_id=1384",
        "keywords": "",
        "description": "",
        "emails": []
      }
    ],
    "emails": [],
    "timeTaken": "36.15s"
  }
]